{
  "view_activities": {
    "precision": 0.8888888888888888,
    "recall": 1.0,
    "f1-score": 0.9411764705882353,
    "support": 8,
    "confused_with": {}
  },
  "modify_category": {
    "precision": 1.0,
    "recall": 1.0,
    "f1-score": 1.0,
    "support": 8,
    "confused_with": {}
  },
  "affirm": {
    "precision": 0.0,
    "recall": 0.0,
    "f1-score": 0.0,
    "support": 2,
    "confused_with": {
      "mood_unhappy": 1,
      "greet": 1
    }
  },
  "clean_activities": {
    "precision": 1.0,
    "recall": 1.0,
    "f1-score": 1.0,
    "support": 3,
    "confused_with": {}
  },
  "view_categories": {
    "precision": 1.0,
    "recall": 1.0,
    "f1-score": 1.0,
    "support": 3,
    "confused_with": {}
  },
  "ask_name": {
    "precision": 0.0,
    "recall": 0.0,
    "f1-score": 0.0,
    "support": 3,
    "confused_with": {
      "bot_challenge": 2,
      "presentation": 1
    }
  },
  "help": {
    "precision": 0.5,
    "recall": 0.5,
    "f1-score": 0.5,
    "support": 2,
    "confused_with": {
      "view_activities": 1
    }
  },
  "mood_great": {
    "precision": 1.0,
    "recall": 0.3333333333333333,
    "f1-score": 0.5,
    "support": 3,
    "confused_with": {
      "mood_unhappy": 1,
      "help": 1
    }
  },
  "add_item": {
    "precision": 1.0,
    "recall": 0.9821428571428571,
    "f1-score": 0.9909909909909909,
    "support": 56,
    "confused_with": {
      "set_status_activity": 1
    }
  },
  "remove_category": {
    "precision": 1.0,
    "recall": 1.0,
    "f1-score": 1.0,
    "support": 12,
    "confused_with": {}
  },
  "deny": {
    "precision": 1.0,
    "recall": 0.6666666666666666,
    "f1-score": 0.8,
    "support": 3,
    "confused_with": {
      "ask_name": 1
    }
  },
  "goodbye": {
    "precision": 0.0,
    "recall": 0.0,
    "f1-score": 0.0,
    "support": 2,
    "confused_with": {
      "greet": 1,
      "inform": 1
    }
  },
  "modify_activity_deadline": {
    "precision": 1.0,
    "recall": 1.0,
    "f1-score": 1.0,
    "support": 12,
    "confused_with": {}
  },
  "remind_me_of": {
    "precision": 1.0,
    "recall": 1.0,
    "f1-score": 1.0,
    "support": 7,
    "confused_with": {}
  },
  "presentation": {
    "precision": 0.9230769230769231,
    "recall": 1.0,
    "f1-score": 0.9600000000000001,
    "support": 36,
    "confused_with": {}
  },
  "greet": {
    "precision": 0.0,
    "recall": 0.0,
    "f1-score": 0.0,
    "support": 2,
    "confused_with": {
      "goodbye": 2
    }
  },
  "remove_item": {
    "precision": 1.0,
    "recall": 1.0,
    "f1-score": 1.0,
    "support": 23,
    "confused_with": {}
  },
  "inform": {
    "precision": 0.9767441860465116,
    "recall": 0.9545454545454546,
    "f1-score": 0.9655172413793104,
    "support": 44,
    "confused_with": {
      "presentation": 2
    }
  },
  "set_status_activity": {
    "precision": 0.9411764705882353,
    "recall": 1.0,
    "f1-score": 0.9696969696969697,
    "support": 16,
    "confused_with": {}
  },
  "bot_challenge": {
    "precision": 0.3333333333333333,
    "recall": 1.0,
    "f1-score": 0.5,
    "support": 1,
    "confused_with": {}
  },
  "mood_unhappy": {
    "precision": 0.5,
    "recall": 1.0,
    "f1-score": 0.6666666666666666,
    "support": 2,
    "confused_with": {}
  },
  "add_category": {
    "precision": 1.0,
    "recall": 1.0,
    "f1-score": 1.0,
    "support": 11,
    "confused_with": {}
  },
  "modify_activity_name": {
    "precision": 1.0,
    "recall": 1.0,
    "f1-score": 1.0,
    "support": 21,
    "confused_with": {}
  },
  "modify_activity_category": {
    "precision": 1.0,
    "recall": 1.0,
    "f1-score": 1.0,
    "support": 17,
    "confused_with": {}
  },
  "accuracy": 0.9461279461279462,
  "macro avg": {
    "precision": 0.7526341584139122,
    "recall": 0.7681953463203463,
    "f1-score": 0.7414186808050904,
    "support": 297
  },
  "weighted avg": {
    "precision": 0.9417871427295352,
    "recall": 0.9461279461279462,
    "f1-score": 0.9404584199642285,
    "support": 297
  }
}